flake8_simplify-stubs/METADATA.toml
flake8_simplify-stubs/__init__.pyi
flake8_simplify-stubs/constants.pyi
flake8_simplify-stubs/py.typed
flake8_simplify-stubs/utils.pyi
flake8_simplify-stubs/rules/__init__.pyi
flake8_simplify-stubs/rules/ast_assign.pyi
flake8_simplify-stubs/rules/ast_bool_op.pyi
flake8_simplify-stubs/rules/ast_call.pyi
flake8_simplify-stubs/rules/ast_classdef.pyi
flake8_simplify-stubs/rules/ast_compare.pyi
flake8_simplify-stubs/rules/ast_expr.pyi
flake8_simplify-stubs/rules/ast_for.pyi
flake8_simplify-stubs/rules/ast_if.pyi
flake8_simplify-stubs/rules/ast_ifexp.pyi
flake8_simplify-stubs/rules/ast_subscript.pyi
flake8_simplify-stubs/rules/ast_try.pyi
flake8_simplify-stubs/rules/ast_unary_op.pyi
flake8_simplify-stubs/rules/ast_with.pyi
types_flake8_simplify-0.30.0.20260108.dist-info/licenses/LICENSE
types_flake8_simplify-0.30.0.20260108.dist-info/METADATA
types_flake8_simplify-0.30.0.20260108.dist-info/WHEEL
types_flake8_simplify-0.30.0.20260108.dist-info/top_level.txt
types_flake8_simplify-0.30.0.20260108.dist-info/RECORD
